odoo/addons/mail_template_multi_company/README.rst
odoo/addons/mail_template_multi_company/__init__.py
odoo/addons/mail_template_multi_company/__manifest__.py
odoo/addons/mail_template_multi_company/i18n/mail_template_multi_company.pot
odoo/addons/mail_template_multi_company/models/__init__.py
odoo/addons/mail_template_multi_company/models/mail_template.py
odoo/addons/mail_template_multi_company/readme/CONFIGURE.rst
odoo/addons/mail_template_multi_company/readme/CONTRIBUTORS.rst
odoo/addons/mail_template_multi_company/readme/DESCRIPTION.rst
odoo/addons/mail_template_multi_company/readme/USAGE.rst
odoo/addons/mail_template_multi_company/security/mail_template.xml
odoo/addons/mail_template_multi_company/static/description/icon.png
odoo/addons/mail_template_multi_company/static/description/index.html
odoo/addons/mail_template_multi_company/views/mail_template.xml
odoo12_addon_mail_template_multi_company-12.0.1.0.1.99.dev2.dist-info/METADATA
odoo12_addon_mail_template_multi_company-12.0.1.0.1.99.dev2.dist-info/WHEEL
odoo12_addon_mail_template_multi_company-12.0.1.0.1.99.dev2.dist-info/top_level.txt
odoo12_addon_mail_template_multi_company-12.0.1.0.1.99.dev2.dist-info/RECORD
